stkweight/__init__.py
stkweight/b_analyse.py
stkweight/core.py
stkweight/log.py
stkweight/server/__init__.py
stkweight/server/__main__.py
stkweight/server/server.py
stkweight/server/models/__init__.py
stkweight/server/models/models.py
stkweight/server/routers/__init__.py
stkweight/server/routers/admin.py
stkweight/server/routers/user.py
stkweight/server/routers/work.py
stkweight/server/utils/__init__.py
stkweight/server/utils/auth_backends.py
stkweight/server/utils/database.py
stkweight/server/utils/user_manager.py
stkweight/view/__init__.py
stkweight/view/view_server.py
stkweight-0.1.4.dist-info/METADATA
stkweight-0.1.4.dist-info/WHEEL
stkweight-0.1.4.dist-info/top_level.txt
stkweight-0.1.4.dist-info/RECORD
